{
  "info": {
    "_postman_id": "7f9f4f42-7e6d-45d8-9e74-9af78feaf010",
    "name": "Task Management App API",
    "description": "Postman collection for login, users, tasks, root health check, and chatbot endpoints.",
    "schema": "https://schema.getpostman.com/json/collection/v2.1.0/collection.json"
  },
  "variable": [
    {
      "key": "baseUrl",
      "value": "http://localhost:8000"
    },
    {
      "key": "token",
      "value": ""
    }
  ],
  "item": [
    {
      "name": "Health",
      "item": [
        {
          "name": "Root Health Check",
          "request": {
            "method": "GET",
            "header": [],
            "url": {
              "raw": "{{baseUrl}}/",
              "host": ["{{baseUrl}}"],
              "path": []
            }
          },
          "response": [
            {
              "name": "200 OK",
              "status": "OK",
              "code": 200,
              "body": "{\n  \"message\": \"Connected to PostgreSQL successfully!\"\n}"
            }
          ]
        }
      ]
    },
    {
      "name": "Authentication",
      "item": [
        {
          "name": "Login",
          "request": {
            "method": "POST",
            "header": [
              {
                "key": "Content-Type",
                "value": "application/json"
              }
            ],
            "body": {
              "mode": "raw",
              "raw": "{\n  \"username\": \"venesa\",\n  \"password\": \"123456\"\n}"
            },
            "url": {
              "raw": "{{baseUrl}}/login",
              "host": ["{{baseUrl}}"],
              "path": ["login"]
            }
          },
          "response": [
            {
              "name": "200 OK",
              "status": "OK",
              "code": 200,
              "body": "{\n  \"access_token\": \"<jwt-token>\",\n  \"token_type\": \"bearer\"\n}"
            }
          ]
        }
      ]
    },
    {
      "name": "Users",
      "item": [
        {
          "name": "Get Users",
          "request": {
            "method": "GET",
            "header": [],
            "url": {
              "raw": "{{baseUrl}}/users",
              "host": ["{{baseUrl}}"],
              "path": ["users"]
            }
          },
          "response": [
            {
              "name": "200 OK",
              "status": "OK",
              "code": 200,
              "body": "[\n  {\n    \"id\": 1,\n    \"name\": \"Venesa Hutajulu\",\n    \"username\": \"venesa\"\n  }\n]"
            }
          ]
        },
        {
          "name": "Create User",
          "request": {
            "method": "POST",
            "header": [
              {
                "key": "Content-Type",
                "value": "application/json"
              }
            ],
            "body": {
              "mode": "raw",
              "raw": "{\n  \"name\": \"New User\",\n  \"username\": \"newuser\",\n  \"password\": \"password123\"\n}"
            },
            "url": {
              "raw": "{{baseUrl}}/users",
              "host": ["{{baseUrl}}"],
              "path": ["users"]
            }
          },
          "response": [
            {
              "name": "200 OK",
              "status": "OK",
              "code": 200,
              "body": "{\n  \"id\": 4,\n  \"name\": \"New User\",\n  \"username\": \"newuser\"\n}"
            }
          ]
        }
      ]
    },
    {
      "name": "Tasks",
      "item": [
        {
          "name": "Get Tasks",
          "request": {
            "method": "GET",
            "header": [
              {
                "key": "Authorization",
                "value": "Bearer {{token}}"
              }
            ],
            "url": {
              "raw": "{{baseUrl}}/tasks",
              "host": ["{{baseUrl}}"],
              "path": ["tasks"]
            }
          },
          "response": [
            {
              "name": "200 OK",
              "status": "OK",
              "code": 200,
              "body": "[\n  {\n    \"id\": 1,\n    \"title\": \"Build task dashboard\",\n    \"description\": \"Create a polished overview page with task metrics.\",\n    \"status\": \"In Progress\",\n    \"deadline\": \"2026-07-16\",\n    \"assignee\": {\n      \"id\": 1,\n      \"name\": \"Venesa Hutajulu\"\n    }\n  }\n]"
            }
          ]
        },
        {
          "name": "Create Task",
          "request": {
            "method": "POST",
            "header": [
              {
                "key": "Authorization",
                "value": "Bearer {{token}}"
              },
              {
                "key": "Content-Type",
                "value": "application/json"
              }
            ],
            "body": {
              "mode": "raw",
              "raw": "{\n  \"title\": \"Review UI\",\n  \"description\": \"Polish frontend layout\",\n  \"status\": \"Todo\",\n  \"deadline\": \"2026-07-20\",\n  \"assignee_id\": 1\n}"
            },
            "url": {
              "raw": "{{baseUrl}}/tasks",
              "host": ["{{baseUrl}}"],
              "path": ["tasks"]
            }
          },
          "response": [
            {
              "name": "200 OK",
              "status": "OK",
              "code": 200,
              "body": "{\n  \"id\": 4,\n  \"title\": \"Review UI\",\n  \"description\": \"Polish frontend layout\",\n  \"status\": \"Todo\",\n  \"deadline\": \"2026-07-20\",\n  \"assignee\": {\n    \"id\": 1,\n    \"name\": \"Venesa Hutajulu\"\n  }\n}"
            }
          ]
        },
        {
          "name": "Update Task",
          "request": {
            "method": "PUT",
            "header": [
              {
                "key": "Authorization",
                "value": "Bearer {{token}}"
              },
              {
                "key": "Content-Type",
                "value": "application/json"
              }
            ],
            "body": {
              "mode": "raw",
              "raw": "{\n  \"title\": \"Review UI v2\",\n  \"description\": \"Improve spacing\",\n  \"status\": \"In Progress\",\n  \"deadline\": \"2026-07-21\",\n  \"assignee_id\": 1\n}"
            },
            "url": {
              "raw": "{{baseUrl}}/tasks/1",
              "host": ["{{baseUrl}}"],
              "path": ["tasks", "1"]
            }
          }
        },
        {
          "name": "Update Task Status",
          "request": {
            "method": "PATCH",
            "header": [
              {
                "key": "Authorization",
                "value": "Bearer {{token}}"
              },
              {
                "key": "Content-Type",
                "value": "application/json"
              }
            ],
            "body": {
              "mode": "raw",
              "raw": "{\n  \"status\": \"Done\"\n}"
            },
            "url": {
              "raw": "{{baseUrl}}/tasks/1/status",
              "host": ["{{baseUrl}}"],
              "path": ["tasks", "1", "status"]
            }
          }
        },
        {
          "name": "Delete Task",
          "request": {
            "method": "DELETE",
            "header": [
              {
                "key": "Authorization",
                "value": "Bearer {{token}}"
              }
            ],
            "url": {
              "raw": "{{baseUrl}}/tasks/1",
              "host": ["{{baseUrl}}"],
              "path": ["tasks", "1"]
            }
          },
          "response": [
            {
              "name": "200 OK",
              "status": "OK",
              "code": 200,
              "body": "{\n  \"message\": \"Task deleted successfully\"\n}"
            }
          ]
        }
      ]
    },
    {
      "name": "Chatbot",
      "item": [
        {
          "name": "Ask Chatbot",
          "request": {
            "method": "POST",
            "header": [
              {
                "key": "Content-Type",
                "value": "application/json"
              }
            ],
            "body": {
              "mode": "raw",
              "raw": "{\n  \"message\": \"Berapa jumlah task yang sudah selesai?\"\n}"
            },
            "url": {
              "raw": "{{baseUrl}}/chat",
              "host": ["{{baseUrl}}"],
              "path": ["chat"]
            }
          },
          "response": [
            {
              "name": "200 OK",
              "status": "OK",
              "code": 200,
              "body": "{\n  \"answer\": \"Ada 1 task yang sudah selesai.\"\n}"
            }
          ]
        }
      ]
    }
  ]
}
